{"title": "SF Dip", "description": "3-D dip estimation by plane wave destruction", "authors": [{"name": "Ricardo Biloti", "email": "biloti@unicamp.br", "institution": "University of Campinas", "homepage": "https://www.ime.unicamp.br/~biloti"}], "tags": ["rsf", "madagascar", "filtering, transforms and attributes"], "programs": [{"enabled": true, "program": {"title": "SF Dip", "description": "3-D dip estimation by plane wave destruction", "authors": [{"name": "Madagascar", "institution": "University of Texas at Austin", "homepage": "https://www.reproducibility.org/"}], "url": "http://reproducibility.org/blog/2012/06/02/program-of-the-month-sfdip/", "executable": "sfdip", "io": {"stdin": true, "stdout": true, "stderr": true}, "parameters": [{"type": "flag", "keyword": "both=y", "description": "Compute both left and right predictions", "default": false, "multiple": false}, {"type": "flag", "keyword": "drift=y", "description": "Shift filter", "default": false, "multiple": false}, {"type": "float", "keyword": "eps=", "description": "Regularization", "default": 0, "required": false, "multiple": false}, {"type": "file", "keyword": "mask=", "description": "Mask file", "required": false, "multiple": false, "placeholder": "RSF file", "filePattern": "*.rsf", "fileType": "RSF"}, {"type": "integer", "keyword": "liter=", "description": "Number of linear iterations", "default": 20, "required": false, "multiple": false}, {"type": "enum", "keyword": "n4=", "description": "Compute mode", "default": "2", "required": false, "multiple": false, "options": [{"description": "in-line", "value": "0"}, {"description": "cross-line", "value": "1"}, {"description": "both", "value": "2"}]}, {"type": "integer", "keyword": "niter=", "description": "Number of iterations", "default": 5, "required": false, "multiple": false}, {"type": "integer", "keyword": "order=", "description": "Accuracy order", "default": 1, "required": false, "multiple": false}, {"type": "integer", "keyword": "rect1=", "description": "Dip smoothness on 1st axis", "default": 1, "required": false, "multiple": false}, {"type": "integer", "keyword": "rect2=", "description": "Dip smoothness on 2nd axis", "default": 1, "required": false, "multiple": false}, {"type": "integer", "keyword": "rect3=", "description": "Dip smoothness on 3rd axis", "default": 1, "required": false, "multiple": false}, {"type": "flag", "keyword": "verb=y", "description": "Be more verbose", "default": false, "multiple": false}, {"type": "section", "title": "In-line"}, {"type": "integer", "keyword": "nj1=", "description": "In-line antialiasing", "default": 1, "required": false, "multiple": false}, {"type": "float", "keyword": "p0=", "description": "Initial in-line dip", "default": 0, "required": false, "multiple": false}, {"type": "float", "keyword": "pmin=", "description": "Minimum in-line dip", "required": false, "multiple": false}, {"type": "float", "keyword": "pmax=", "description": "Maximum in-line dip", "required": false, "multiple": false}, {"type": "file", "keyword": "idip=", "description": "In-line dip file", "required": false, "multiple": false, "placeholder": "RSF file", "filePattern": "*.rsf", "fileType": "RSF"}, {"type": "section", "title": "Cross-line"}, {"type": "integer", "keyword": "nj2=", "description": "Cross-line antialiasing", "default": 1, "required": false, "multiple": false}, {"type": "float", "keyword": "10=", "description": "Initial cross-line dip", "default": 0, "required": false, "multiple": false}, {"type": "float", "keyword": "qmin=", "description": "Minimum cross-line dip", "required": false, "multiple": false}, {"type": "float", "keyword": "qmax=", "description": "Maximum cross-line dip", "required": false, "multiple": false}, {"type": "file", "keyword": "xdip=", "description": "Initial cross-line dip file", "required": false, "multiple": false, "placeholder": "RSF file", "filePattern": "*.rsf", "fileType": "RSF"}]}}]}